<PAMDataset>
  <PAMRasterBand band="1">
    <Description>LST</Description>
    <Histograms>
      <HistItem>
        <HistMin>24.35332625396131</HistMin>
        <HistMax>36.7259701601086</HistMax>
        <BucketCount>256</BucketCount>
        <IncludeOutOfRange>1</IncludeOutOfRange>
        <Approximate>0</Approximate>
        <HistCounts>6|6|2|7|5|5|11|5|13|13|33|32|58|62|74|87|123|132|135|154|228|190|197|214|231|254|254|295|271|297|383|371|417|418|446|428|482|466|492|493|510|505|519|535|552|572|583|633|649|632|694|716|739|681|669|719|627|641|627|679|617|640|667|641|716|656|744|651|700|658|755|748|720|722|697|700|702|694|645|662|686|646|606|601|592|551|526|576|572|529|564|539|589|550|487|497|535|513|504|552|581|485|518|506|495|527|505|521|489|483|517|485|502|512|516|499|494|461|441|441|452|389|389|406|365|361|339|335|318|301|302|287|293|245|256|270|247|236|266|208|210|170|186|154|135|137|123|108|100|109|102|105|116|90|82|74|51|41|60|38|44|28|26|38|39|29|42|28|23|31|36|25|17|35|21|27|27|24|18|23|26|16|21|13|17|21|23|18|27|25|16|25|17|15|26|10|12|20|17|16|17|8|9|10|8|7|10|6|7|7|5|11|8|7|4|5|4|7|8|3|7|5|4|3|3|8|1|4|4|5|1|2|6|2|5|3|3|2|4|2|1|2|5|3|1|4|2|4|2|0|5|0|1|2|3|1</HistCounts>
      </HistItem>
    </Histograms>
    <Metadata>
      <MDI key="STATISTICS_MINIMUM">24.353326253961</MDI>
      <MDI key="STATISTICS_MAXIMUM">36.725970160109</MDI>
      <MDI key="STATISTICS_MEAN">28.304949415095</MDI>
      <MDI key="STATISTICS_STDDEV">1.7382521192058</MDI>
      <MDI key="STATISTICS_MEDIAN">28.089380</MDI>
      <MDI key="STATISTICS_COUNT">64879.000000</MDI>
      <MDI key="STATISTICS_SKIPFACTORX">1</MDI>
      <MDI key="STATISTICS_SKIPFACTORY">1</MDI>
      <MDI key="STATISTICS_EXCLUDEDVALUES"></MDI>
      <MDI key="STATISTICS_COVARIANCES">3.021520429923344</MDI>
    </Metadata>
  </PAMRasterBand>
</PAMDataset>
