<PAMDataset>
  <PAMRasterBand band="1">
    <Metadata>
      <MDI key="STATISTICS_MINIMUM">0.21296374258933</MDI>
      <MDI key="STATISTICS_MAXIMUM">0.84314026393365</MDI>
      <MDI key="STATISTICS_MEAN">0.6114249848244</MDI>
      <MDI key="STATISTICS_STDDEV">0.082819517293558</MDI>
      <MDI key="STATISTICS_MEDIAN">nan</MDI>
      <MDI key="STATISTICS_COUNT">35777.000000</MDI>
      <MDI key="STATISTICS_SKIPFACTORX">1</MDI>
      <MDI key="STATISTICS_SKIPFACTORY">1</MDI>
      <MDI key="STATISTICS_EXCLUDEDVALUES"></MDI>
      <MDI key="STATISTICS_COVARIANCES">0.006859072444737956</MDI>
    </Metadata>
  </PAMRasterBand>
</PAMDataset>
